Workbook

Sheet Dashboard
B1: Nibby Baby (Omer) — Leo Israel account
B2: Statement dated 30 Sep 2026 and invoice SF01078. All amounts are US dollars. Source PDFs: balance 01.10.26.pdf, 025-204 invoice.pdf.
B4: YOU OWE NOW | E4: Shipment total (Sep 2026) | H4: Advance paid (3 Sep) | J4: Invoice SF01078 (30 Sep)
B5: =History!I14 | E5: =D10+D12 | H5: =E11 | J5: =Invoice!F18
B8: September 2026 shipment — what is open
B9: Date | C9: What happened | D9: You owe (+) | E9: You paid (−) | F9: Balance
B10: =History!B11 | C10: =History!D11 | D10: =IF(History!E11>0,History!E11,"") | E10: =IF(History!F11>0,History!F11,"") | F10: =History!I11 | M10: Invoice 1 Sep | N10: =D10
B11: =History!B12 | C11: =History!D12 | D11: =IF(History!E12>0,History!E12,"") | E11: =IF(History!F12>0,History!F12,"") | F11: =History!I12 | M11: Advance 3 Sep | N11: =E11
B12: =History!B13 | C12: =History!D13 | D12: =IF(History!E13>0,History!E13,"") | E12: =IF(History!F13>0,History!F13,"") | F12: =History!I13 | M12: Invoice 30 Sep | N12: =D12
B13: Remaining balance | D13: =SUM(D10:D12) | E13: =SUM(E10:E12) | F13: =D13-E13 | M13: You owe now | N13: =F13
B14: Shipment $69,800.14 − advance $19,250.00 = $50,550.14 still to pay. Everything before 2026 was settled in full on 8 Jan 2024 (see History).
B16: Invoice SF01078 — 30 Sep 2026
B17: Model | C17: Pieces | D17: Price / piece | E17: Before VAT | F17: With 10% VAT
B18: =Invoice!B12 | C18: =Invoice!C12 | D18: =Invoice!D12 | E18: =Invoice!E12 | F18: =Invoice!F12 | M18: 204 MODEL | N18: =F18
B19: =Invoice!B13 | C19: =Invoice!C13 | D19: =Invoice!D13 | E19: =Invoice!E13 | F19: =Invoice!F13 | M19: 025 MODEL | N19: =F19
B20: Invoice total | D20: =Invoice!C12+Invoice!C13 | E20: =Invoice!F15 | F20: =Invoice!F18
B21: 18,278 pieces. Turkish VAT 10% is included in the total. This invoice is the 30 Sep line above.
B23: How to read
B24: • Omer's accounting software prints “TL” next to every number, but the figures are US dollars: the unit prices ($2.14, $2.02) match his dollar price list, and the 1 Sep invoice equals the first-shipment total $26,071.24 + 10% VAT.
B25: • “You owe” = an invoice from Nibby Baby. “You paid” = cash you already sent.
B26: • The Turkish PDF lists newest first and its running-balance column is not a true balance. The History sheet is oldest-first with a real running balance and matches the PDF totals.

Sheet History
B1: Full account history — oldest first
B2: Account CR00044, Leo Israel at Nibby Baby. Amounts exactly as printed on the statement (US dollars).
B5: Date | C5: Type | D5: Description | E5: Invoice | F5: Payment | I5: Balance | J5: After this line
B6: 45219 | C6: Invoice | D6: Models 204 and 025 | E6: 25004.58 | I6: =N(E6)-N(F6) | J6: =IF(ABS(I6)<0.005,"Account at zero","Still owed")
B7: 45244 | C7: Payment | D7: Cash paid | F7: 6968 | I7: =I6+N(E7)-N(F7) | J7: =IF(ABS(I7)<0.005,"Account at zero","Still owed")
B8: 45254 | C8: Invoice | D8: Model 025 | E8: 23310.72 | I8: =I7+N(E8)-N(F8) | J8: =IF(ABS(I8)<0.005,"Account at zero","Still owed")
B9: 45260 | C9: Payment | D9: Cash paid | F9: 17972.58 | I9: =I8+N(E9)-N(F9) | J9: =IF(ABS(I9)<0.005,"Account at zero","Still owed")
B10: 45299 | C10: Payment | D10: Cash paid — account cleared to zero | F10: 23374.72 | I10: =I9+N(E10)-N(F10) | J10: =IF(ABS(I10)<0.005,"Account at zero","Still owed")
B11: 46266 | C11: Invoice | D11: Models 200, 201, 202 — first shipment | E11: 28678.36 | I11: =I10+N(E11)-N(F11) | J11: =IF(ABS(I11)<0.005,"Account at zero","Still owed")
B12: 46268 | C12: Payment | D12: Advance payment | F12: 19250 | I12: =I11+N(E12)-N(F12) | J12: =IF(ABS(I12)<0.005,"Account at zero","Still owed")
B13: 46295 | C13: Invoice | D13: Models 204 and 025 — invoice SF01078 | E13: 41121.78 | I13: =I12+N(E13)-N(F13) | J13: =IF(ABS(I13)<0.005,"Account at zero","Still owed")
B14: Totals (match the PDF footer) | E14: =SUM(E6:E13) | F14: =SUM(F6:F13) | I14: =I13 | J14: Leo Israel owes this
B16: PDF footer: total invoices 118,115.44 · total payments 67,565.30 · balance 50,550.14 owed (Borç). The totals above reproduce those figures exactly.
B17: Supplier: Nibby Baby, Kazımkarabekir Mh. Kızılcık Sk. No. 18-24 · phone 0538 378 58 86 · report printed 30 Sep 2026 17:45.

Sheet Invoice
B1: Invoice SF01078 — 30 Sep 2026, 17:40
B2: Nibby Baby (Omer) to Leo Israel. US dollars. Unit prices are before Turkish VAT (10%).
B4: Customer | C4: Leo Israel
B5: Supplier | C5: Nibby Baby (Omer), Turkey
B6: Invoice no. | C6: SF01078
B7: Date | C7: 46295
B8: VAT | C8: 0.1
B11: Model | C11: Pieces | D11: Price / piece | E11: Before VAT | F11: With VAT
B12: 204 MODEL | C12: 3849 | D12: 2.14 | E12: =C12*D12 | F12: 9060.55
B13: 025 MODEL | C13: 14429 | D13: 2.02 | E13: =C13*D13 | F13: 32061.24
B15: Before VAT (VAT base) | F15: =SUM(E12:E13)
B16: VAT 10% | F16: =ROUND(F15*$C$8,2)
B18: TOTAL TO PAY | E18: =C12+C13 | F18: =F15+F16
B20: Printed line totals (9,060.55 + 32,061.24) add to 41,121.79; the official total is 41,121.78 because VAT was rounded once on the whole invoice.
B21: The PDF prints the currency as TL and the amount in words in Turkish, but the figures are US dollars (see Dashboard notes). Barcode at top reads 1 413000 000000.
